scri/__init__.py
scri/__version__.py
scri/bms_transformations.py
scri/extrapolation.py
scri/flux.py
scri/mode_calculations.py
scri/modes_time_series.py
scri/plotting.py
scri/rotations.py
scri/sample_waveforms.py
scri/utilities.py
scri/waveform_base.py
scri/waveform_grid.py
scri/waveform_modes.py
scri/LVC/__init__.py
scri/LVC/file_io.py
scri/SpEC/__init__.py
scri/SpEC/com_motion.py
scri/SpEC/find_com_in_catalog.py
scri/SpEC/remove_avg_com_from_catalog.py
scri/SpEC/file_io/__init__.py
scri/SpEC/file_io/corotating_paired_xor.py
scri/SpEC/file_io/rotating_paired_xor_multishuffle_bzip2.py
scri/SpEC/samples/metadata.txt
scri/asymptotic_bondi_data/__init__.py
scri/asymptotic_bondi_data/bms_charges.py
scri/asymptotic_bondi_data/constraints.py
scri/asymptotic_bondi_data/from_initial_values.py
scri/asymptotic_bondi_data/map_to_abd_frame.py
scri/asymptotic_bondi_data/map_to_superrest_frame.py
scri/asymptotic_bondi_data/transformations.py
scri/pn/__init__.py
scri-2024.0.6.dist-info/METADATA
scri-2024.0.6.dist-info/WHEEL
scri-2024.0.6.dist-info/licenses/LICENSE
scri-2024.0.6.dist-info/RECORD
