Metadata-Version: 2.4
Name: scri
Version: 2024.0.6
Summary: Time-dependent functions of spin-weighted spherical harmonics on future null infinity
Project-URL: Homepage, https://github.com/moble/scri
Project-URL: Documentation, https://scri.readthedocs.io/
Author-email: Michael Boyle <michael.oliver.boyle@gmail.com>
License: The MIT License (MIT)
License-File: LICENSE
Classifier: Development Status :: 5 - Production/Stable
Classifier: Intended Audience :: Science/Research
Classifier: License :: OSI Approved :: MIT License
Classifier: Operating System :: OS Independent
Classifier: Programming Language :: Python :: 3
Classifier: Topic :: Scientific/Engineering :: Astronomy
Classifier: Topic :: Scientific/Engineering :: Physics
Requires-Python: >=3.10
Requires-Dist: h5py>=3
Requires-Dist: numba>=0.60.0
Requires-Dist: numpy-quaternion>=2024.0.2
Requires-Dist: numpy>=2.0
Requires-Dist: scipy>=1.13
Requires-Dist: spherical-functions>=2022.4
Requires-Dist: spinsfast>=2022.4
Requires-Dist: sxs>=2022.4.0
Requires-Dist: tqdm>=4.63.1
